__init__.py
pypurge/__init__.py
pypurge/banner.py
pypurge/cli.py
pypurge/modules/__init__.py
pypurge/modules/args.py
pypurge/modules/backup.py
pypurge/modules/completions.py
pypurge/modules/config.py
pypurge/modules/config_wizard.py
pypurge/modules/deletion.py
pypurge/modules/locking.py
pypurge/modules/logging.py
pypurge/modules/safety.py
pypurge/modules/scan.py
pypurge/modules/ui.py
pypurge/modules/utils.py
pypurge-4.0.1.dist-info/METADATA
pypurge-4.0.1.dist-info/WHEEL
pypurge-4.0.1.dist-info/entry_points.txt
pypurge-4.0.1.dist-info/top_level.txt
pypurge-4.0.1.dist-info/RECORD
