Metadata-Version: 2.4
Name: pypurge
Version: 4.0.1
Summary: Safe Python project cleanup utility — purge caches, build artifacts, test leftovers, and env clutter with smart protection.
Author-email: Dhruv <dhruv13x@gmail.com>
Maintainer-email: Dhruv <dhruv13x@gmail.com>
License: MIT
Project-URL: Homepage, https://github.com/dhruv13x/pypurge
Project-URL: Repository, https://github.com/dhruv13x/pypurge.git
Project-URL: Issues, https://github.com/dhruv13x/pypurge/issues
Keywords: cleanup,cache,purge,pycache,dev-tools,cli,maintenance,automation,project-cleaner
Classifier: Development Status :: 4 - Beta
Classifier: Environment :: Console
Classifier: Intended Audience :: Developers
Classifier: Topic :: Software Development :: Build Tools
Classifier: Topic :: Software Development :: Libraries
Classifier: Topic :: System :: Systems Administration
Classifier: License :: OSI Approved :: MIT License
Classifier: Operating System :: OS Independent
Classifier: Programming Language :: Python :: 3
Requires-Python: >=3.8
Requires-Dist: rich>=13.0.0
Requires-Dist: pathspec>=0.12.0
Requires-Dist: jsonschema>=4.20.0
Provides-Extra: dev
Requires-Dist: pytest>=8.0.0; extra == "dev"
Requires-Dist: pytest-cov>=5.0.0; extra == "dev"
Requires-Dist: pytest-timeout>=2.2.0; extra == "dev"
Requires-Dist: pytest-json-report>=1.5.0; extra == "dev"
Requires-Dist: pytest-asyncio>=0.23.0; extra == "dev"
Requires-Dist: pytest-mock>=3.10.0; extra == "dev"
Requires-Dist: pyfakefs>=5.0.0; extra == "dev"
Requires-Dist: ruff>=0.6.0; extra == "dev"
Requires-Dist: black>=24.3.0; extra == "dev"
Requires-Dist: mypy>=1.11.0; extra == "dev"
Requires-Dist: PyYAML>=6.0; extra == "dev"
Requires-Dist: types-PyYAML>=6.0; extra == "dev"
